fapify.py
fapify-1.1.8.dist-info/METADATA
fapify-1.1.8.dist-info/WHEEL
fapify-1.1.8.dist-info/entry_points.txt
fapify-1.1.8.dist-info/top_level.txt
fapify-1.1.8.dist-info/RECORD
