Metadata-Version: 2.4
Name: fapify
Version: 1.1.8
Summary: Download photos and videos from leakedzone.com
Home-page: https://github.com/andrilchakraborty/fapify
Author: Cassidy
License: MIT
Requires-Python: >=3.7
Requires-Dist: aiohttp
Requires-Dist: beautifulsoup4
Requires-Dist: tabulate
Requires-Dist: colorama
